README.rst
setup.py
noseapp_daemon/__init__.py
noseapp_daemon/management.py
noseapp_daemon/presets.py
noseapp_daemon/runner.py
noseapp_daemon/service.py
noseapp_daemon/utils.py
noseapp_daemon.egg-info/PKG-INFO
noseapp_daemon.egg-info/SOURCES.txt
noseapp_daemon.egg-info/dependency_links.txt
noseapp_daemon.egg-info/not-zip-safe
noseapp_daemon.egg-info/requires.txt
noseapp_daemon.egg-info/top_level.txt
tests/__init__.py
tests/daemon.py
tests/management.py
tests/runner.py
tests/service.py