Metadata-Version: 1.1
Name: noseapp-daemon
Version: 2.3.0
Summary: noseapp extension for linux daemon testing
Home-page: https://github.com/trifonovmixail/noseapp_daemon
Author: Mikhail Trifonov
Author-email: mikhail.trifonov@corp.mail.ru
License: GNU LGPL
Platform: linux
Classifier: Development Status :: 4 - Beta
Classifier: Intended Audience :: Developers
Classifier: Programming Language :: Python
Classifier: Programming Language :: Python :: 2.7
Classifier: Topic :: Software Development :: Testing
